flake8_docstrings.py
flake8_docstrings-1.7.0.dist-info/LICENSE
flake8_docstrings-1.7.0.dist-info/METADATA
flake8_docstrings-1.7.0.dist-info/WHEEL
flake8_docstrings-1.7.0.dist-info/entry_points.txt
flake8_docstrings-1.7.0.dist-info/top_level.txt
flake8_docstrings-1.7.0.dist-info/RECORD
