Metadata-Version: 2.1
Name: flake8-docstrings
Version: 1.7.0
Summary: Extension for flake8 which uses pydocstyle to check docstrings
Home-page: https://github.com/pycqa/flake8-docstrings
Author: Simon ANDRÉ
Author-email: sandre@anybox.fr
Maintainer: Ian Cordasco
Maintainer-email: graffatcolmingov@gmail.com
License: MIT
Keywords: PEP 257,pydocstyle,pep257,docstrings,flake8
Classifier: Environment :: Console
Classifier: Intended Audience :: Developers
Classifier: License :: OSI Approved :: MIT License
Classifier: Operating System :: OS Independent
Classifier: Programming Language :: Python :: 3
Classifier: Programming Language :: Python :: 3 :: Only
Classifier: Programming Language :: Python :: Implementation :: CPython
Provides: flake8_docstrings
Requires-Python: >=3.7
License-File: LICENSE
